unicode_blocks/__init__.py
unicode_blocks/blocks.py
unicode_blocks/charNormaliser.py
unicode_blocks/cjk.py
unicode_blocks/errors.py
unicode_blocks/globals.py
unicode_blocks/unicodeBlock.py
unicode_blocks_py-17.0.0.dist-info/licenses/LICENSE
unicode_blocks_py-17.0.0.dist-info/METADATA
unicode_blocks_py-17.0.0.dist-info/WHEEL
unicode_blocks_py-17.0.0.dist-info/top_level.txt
unicode_blocks_py-17.0.0.dist-info/RECORD
