Metadata-Version: 2.4
Name: unicode-blocks-py
Version: 17.0.0
Summary: Unicode blocks data utility module
Author-email: NightFurySL2001 <nfsl-fonts@outlook.com>
License-Expression: MIT
Project-URL: Homepage, https://github.com/NightFurySL2001/unicode-blocks-py
Project-URL: Issues, https://github.com/NightFurySL2001/unicode-blocks-py/issues
Classifier: Programming Language :: Python :: 3
Classifier: Operating System :: OS Independent
Classifier: Development Status :: 4 - Beta
Classifier: Intended Audience :: Developers
Classifier: Natural Language :: English
Classifier: Topic :: Software Development :: Libraries :: Python Modules
Requires-Python: >=3.11
License-File: LICENSE
Dynamic: license-file
